README.md
setup.cfg
setup.py
flask_json_content_type_validator/__init__.py
flask_json_content_type_validator/json_content_type_validator.py
flask_json_content_type_validator.egg-info/PKG-INFO
flask_json_content_type_validator.egg-info/SOURCES.txt
flask_json_content_type_validator.egg-info/dependency_links.txt
flask_json_content_type_validator.egg-info/requires.txt
flask_json_content_type_validator.egg-info/top_level.txt
tests/__init__.py
tests/dummy_flask_app.py
tests/json_type_content_validator_tests.py