Metadata-Version: 1.0
Name: flask-json-content-type-validator
Version: 0.1.1
Summary: Flask JSON Content-Type decorator which validates that the Content-Type is indeed application/json. In the case of a wrong content type, then the decorator will throw an exception which can be customized.
Home-page: https://github.com/vklap/flask-json-content-type-validator
Author: Victor Klapholz
Author-email: victor.klapholz@gmail.com
License: MIT
Keywords: flask json content validation decorator
Platform: UNKNOWN
